{
  "claim": "2020-04-14T23:39:40.147Z",
  "expires": "2020-04-16T01:10:16.261Z",
  "tasks": [
    {
      "task": "dVV_3i9uRtinspsPMYdi1A",
      "run": 0
    },
    {
      "task": "ECM17x1UQ4SnDcPXPdGltw",
      "run": 0
    },
    {
      "task": "UDng-RZ-SEa0PHwFPq4Ydw",
      "run": 0
    },
    {
      "task": "HP66tzDWQ9CCWhMLVpxukw",
      "run": 0
    },
    {
      "task": "AwIovo7VTfWvAfbXfqGEqA",
      "run": 0
    },
    {
      "task": "RX7edu2ETmSj0I0j3M8fPg",
      "run": 0
    },
    {
      "task": "XCz0KlH0T4i1k1RPGl_29w",
      "run": 0
    }
  ]
}