{
  "claim": "2020-04-08T11:48:03.875Z",
  "expires": "2020-04-09T12:40:17.544Z",
  "tasks": [
    {
      "task": "AhR9b2bBSZ2ouw_xNyS-pg",
      "run": 0
    },
    {
      "task": "Wt04YSYpSzuSnHxKYRMTNA",
      "run": 0
    },
    {
      "task": "ITd4mGPeQGyvbpHbjY_kzw",
      "run": 0
    },
    {
      "task": "NmsM6dlQRzGEdOR2XxgXXA",
      "run": 0
    },
    {
      "task": "Eu6FO7wLRcS9l8lRaZXKNA",
      "run": 0
    },
    {
      "task": "DrBg4sA0RaatdaGeg0taNQ",
      "run": 0
    },
    {
      "task": "HDrRekSERmGCzQrYIrRW4Q",
      "run": 0
    }
  ]
}