{
  "claim": "2020-04-10T17:52:40.352Z",
  "expires": "2020-04-11T22:47:23.983Z",
  "tasks": [
    {
      "task": "a6sXUsEIS-m24146sHuAKw",
      "run": 0
    },
    {
      "task": "YILQm_aZTQmuxt9n2vNTnQ",
      "run": 0
    },
    {
      "task": "Rw_preXZR2SPNIDCDOcnqQ",
      "run": 0
    },
    {
      "task": "OZB2sn0HQb-o0p-eRXl9Og",
      "run": 0
    },
    {
      "task": "ZyaiFgOWRGCU7IUhRiTpfA",
      "run": 0
    },
    {
      "task": "FaFDGOXXQeumLn8fPSJHWQ",
      "run": 0
    },
    {
      "task": "G2tFpsRrSdakZBywhKpQIg",
      "run": 0
    },
    {
      "task": "IB01t45PTHCpAuG-I7BwRA",
      "run": 0
    },
    {
      "task": "Ogay8DJIRvGlHUA5tRlokA",
      "run": 0
    },
    {
      "task": "b4UTtWSGS6usk9xWP3ehOQ",
      "run": 0
    },
    {
      "task": "ci6QfIW6TkaLkCNcx5vhRQ",
      "run": 0
    },
    {
      "task": "UUf388ntR0Waa_oUJpPROw",
      "run": 0
    },
    {
      "task": "HtL_IBFuTwuRijwn81OJxQ",
      "run": 0
    },
    {
      "task": "I9IcF2x1SOWVs99R6faz8w",
      "run": 0
    }
  ]
}