{
  "claim": "2020-04-15T14:10:03.002Z",
  "expires": "2020-04-16T16:02:44.854Z",
  "tasks": [
    {
      "task": "Uq6jJ6ZzS1So6UsS5XM1SQ",
      "run": 0
    },
    {
      "task": "AHjp6xGfTcejyH4cKGfdrQ",
      "run": 0
    },
    {
      "task": "Ee68S5CQQKmBdiUNfQJAwA",
      "run": 0
    },
    {
      "task": "UiNIGnZLRi-VHzKAUi9qsg",
      "run": 0
    },
    {
      "task": "IAIYo_wERNSuU3t-XAerZA",
      "run": 0
    },
    {
      "task": "LQwwrds8QRqyKQAFo_D6Pw",
      "run": 0
    }
  ]
}