{
  "claim": "2020-04-07T19:57:56.097Z",
  "expires": "2020-04-08T23:25:42.249Z",
  "tasks": [
    {
      "task": "YlYR2aweR1aRDTkBZY1jog",
      "run": 0
    },
    {
      "task": "P8xglAPYSluzR1nRoF70NQ",
      "run": 0
    },
    {
      "task": "dHXRUPxNRWyCboOMjXQ7SA",
      "run": 0
    },
    {
      "task": "QQirKe3ORIO56sAd1CfVxg",
      "run": 0
    },
    {
      "task": "KdilteayT56W7pXqbSlwJg",
      "run": 0
    },
    {
      "task": "ciU_O7hjTs6rPuRepqqEgg",
      "run": 0
    },
    {
      "task": "bH-ViM8wQ4Sck4TJwqwa9Q",
      "run": 0
    }
  ]
}