{
  "claim": "2020-04-08T17:22:25.506Z",
  "expires": "2020-04-09T22:44:47.925Z",
  "tasks": [
    {
      "task": "CqKhd6PCRH6OVN4p33pBLA",
      "run": 0
    },
    {
      "task": "Kq2zZR8ERfu8Nw2uiepctg",
      "run": 0
    },
    {
      "task": "SBoWJTQJTcCnht4FLXenbQ",
      "run": 0
    },
    {
      "task": "edu3DHBiSbuAKF2hIO-WWg",
      "run": 0
    },
    {
      "task": "JUY4Ws1cS7KqhsJdHlvcrw",
      "run": 0
    },
    {
      "task": "M_NKlh-4R82orFmXu2wkJg",
      "run": 0
    },
    {
      "task": "NbGA_b2UQuqKWoQWBakBuw",
      "run": 0
    },
    {
      "task": "bN9iL7VCTAGydQz5IgHBgg",
      "run": 0
    },
    {
      "task": "WQPpJzIjQXWPQxrKhvU-Fw",
      "run": 0
    },
    {
      "task": "RS5tn_S_QVGWvVQtQ5of9Q",
      "run": 0
    },
    {
      "task": "eRvGpVZARW65ZMYsxokPlg",
      "run": 0
    },
    {
      "task": "KSnI9RCVSuuQ8HC975EYNA",
      "run": 0
    },
    {
      "task": "Z2ram6qVRwqArRBSpwQVig",
      "run": 0
    },
    {
      "task": "HP9SqzZJT2CZOokJhqHVBg",
      "run": 0
    }
  ]
}