{
  "claim": "2020-04-08T20:13:18.588Z",
  "expires": "2020-04-09T21:36:06.218Z",
  "tasks": [
    {
      "task": "HuIOTbjmTDGT9yPXYhDG-w",
      "run": 0
    },
    {
      "task": "dTFFWIemRbC-PMJqER7_YA",
      "run": 0
    },
    {
      "task": "QkZVLT5gTfCMico08JSfuw",
      "run": 0
    },
    {
      "task": "CWPJylX_RlivUXXJMeBAnw",
      "run": 0
    },
    {
      "task": "DwTPpaBLSn2xU0dQhlZWHA",
      "run": 0
    },
    {
      "task": "YMEc9XP1RNqQAR7ZzXeoEg",
      "run": 0
    },
    {
      "task": "MHfOSuedSt2VR4-naI9nVA",
      "run": 0
    },
    {
      "task": "Ewf6jxczQoONnZwGbcPXrQ",
      "run": 0
    }
  ]
}