[
  {
    "id": "i-054f27c671c2781a1",
    "launch": "2020-04-11T22:23:32.000Z",
    "claim": "2020-04-12T23:40:43.582Z",
    "tasks": [
      "WTDEMsYtRlSYgzHWjUTh3w/0",
      "X1usHyyhQwKccObwI7Gmhg/0",
      "QqGIO2vWRi-81v40zd3HLg/0"
    ]
  },
  {
    "id": "i-0225052db0d096e48",
    "launch": "2020-04-11T22:19:28.000Z",
    "claim": "2020-04-12T23:32:19.873Z",
    "tasks": [
      "U6GVDGvDSkGDOLyj7uw2gg/0",
      "eqdSma-hTTm2mJ4b4-744Q/0",
      "YhUkMuDqSWm1f2KGLGmaTQ/0"
    ]
  },
  {
    "id": "i-06dba3a5d8ed97ae0",
    "launch": "2020-04-11T23:40:39.000Z",
    "claim": "2020-04-12T23:47:21.399Z",
    "tasks": [
      "e3ivFzJSRdSMXvwOvz2Usg/0"
    ]
  },
  {
    "id": "i-0b79795ac7a5065c0",
    "launch": "2020-04-11T22:18:52.000Z",
    "claim": "2020-04-12T23:22:01.543Z",
    "tasks": [
      "DylkvF6aS_qrgO9sYboZ3g/0",
      "f2Ex1QPwQceK80VxhUfIKg/0",
      "bDqqsNU9SjauayDBJlLkOw/0",
      "fyjamylLSLy50sQasjvJag/0"
    ]
  },
  {
    "id": "i-019d45bd66715a577",
    "launch": "2020-04-11T23:40:36.000Z",
    "claim": "2020-04-12T23:47:29.954Z",
    "tasks": [
      "fNlZ_MNXSBe_HMPWpZ9mFg/0"
    ]
  },
  {
    "id": "i-0a6eb84a8b3c8f687",
    "launch": "2020-04-11T22:01:30.000Z",
    "claim": "2020-04-12T23:42:43.420Z",
    "tasks": [
      "Y33-DJ5jQsOYC7cHjp2bqw/0",
      "LDlOMd0HRCa74O12ZIBRcQ/0",
      "EQ6ZgKC-RvOn6pVclrTfMA/0",
      "Yw_kA0fhQtiDl3QADqRbKA/0"
    ]
  },
  {
    "id": "i-05114436ff3b16f50",
    "launch": "2020-04-11T23:40:23.000Z",
    "claim": "2020-04-12T23:47:20.047Z",
    "tasks": [
      "JC4We0tNQZyFbX-Zo4H02w/0"
    ]
  },
  {
    "id": "i-0ac1a8699a8711fce",
    "launch": "2020-04-11T22:19:02.000Z",
    "claim": "2020-04-12T23:46:23.263Z",
    "tasks": [
      "FtBYx_tSTu-1bhBPKOFf6w/0",
      "KYaeKFoZT1G3Rgr3bpMCkg/0",
      "A1WJUF48Rj668twQ0X6XlA/0",
      "PMkYxQVuTwW3iFH6zKwQNw/0"
    ]
  },
  {
    "id": "i-07442b086e27ca8fd",
    "launch": "2020-04-11T23:24:07.000Z",
    "claim": "2020-04-12T23:45:17.979Z",
    "tasks": [
      "XSw3MfoKRKqRBULrC4JG0Q/0",
      "bdNMFgLuRICCnqJxDDChBw/0"
    ]
  },
  {
    "id": "i-0d444fd362d4ac249",
    "launch": "2020-04-11T23:40:28.000Z",
    "claim": "2020-04-12T23:47:42.713Z",
    "tasks": [
      "UaLgxn3ZTIyl32hlG-Setw/0"
    ]
  },
  {
    "id": "i-0890f1b510caf4167",
    "launch": "2020-04-11T23:10:39.000Z",
    "claim": "2020-04-12T23:40:50.524Z",
    "tasks": [
      "Vu_TmkYCSVGH2KOxdqbKCQ/0",
      "Cs5sn8UfTs6vU4YHtbWj0g/0"
    ]
  },
  {
    "id": "i-0222155ce0e67cf8a",
    "launch": "2020-04-11T23:23:59.000Z",
    "claim": "2020-04-12T23:30:48.689Z",
    "tasks": [
      "A_v8WLxWQDe4JPjTlhSnMg/0"
    ]
  },
  {
    "id": "i-031e75af18b177230",
    "launch": "2020-04-11T23:24:36.000Z",
    "claim": "2020-04-12T23:30:48.177Z",
    "tasks": [
      "JPcMfx0dQX2Y6Yuqs32LsA/0"
    ]
  },
  {
    "id": "i-0038471e7d34e1af2",
    "launch": "2020-04-11T22:18:49.000Z",
    "claim": "2020-04-12T23:47:54.133Z",
    "tasks": [
      "QpMxFnTtSfCd1PACjz_dlA/0",
      "a7HVx89CQ0ebhla7i-vRfw/0",
      "fEXo9VuwQliHs2N6vHVFfg/0",
      "aG04LckQRvqgxEOwk_JFxQ/0"
    ]
  },
  {
    "id": "i-05d9cc1771981e4a4",
    "launch": "2020-04-11T23:11:36.000Z"
  },
  {
    "id": "i-0e631fd91687e1c61",
    "launch": "2020-04-11T23:40:28.000Z",
    "claim": "2020-04-12T23:47:41.239Z",
    "tasks": [
      "ZEfjt0j6R0SCiLIOEGQAkQ/0"
    ]
  },
  {
    "id": "i-09b1143a0e89d987f",
    "launch": "2020-04-11T23:40:23.000Z",
    "claim": "2020-04-12T23:47:20.817Z",
    "tasks": [
      "WgEYbuXPRGSLJaIAf8pQUA/0"
    ]
  },
  {
    "id": "i-0c5fac8095dce8f3d",
    "launch": "2020-04-11T23:40:26.000Z",
    "claim": "2020-04-12T23:47:22.107Z",
    "tasks": [
      "eaqDc6OLSyWxufBg7CUrgA/0"
    ]
  },
  {
    "id": "i-088e97ab051bda7f3",
    "launch": "2020-04-11T21:59:18.000Z",
    "claim": "2020-04-12T23:22:14.209Z",
    "tasks": [
      "f1CMOwjgQCeoKBPC86eAHQ/0",
      "f83FCdneTfiMLfqHZOpnnA/0",
      "HspVUyy_TXuSzBkTlFFpqA/0",
      "MOttCb7cRZCwoo1O9tMOaA/0"
    ]
  },
  {
    "id": "i-0e518832e03bf44ed",
    "launch": "2020-04-11T23:40:30.000Z",
    "claim": "2020-04-12T23:47:18.257Z",
    "tasks": [
      "IIYJWm2LQrOe8ZKHvfKKeQ/0"
    ]
  },
  {
    "id": "i-041cd1dc3cdbf0a1b",
    "launch": "2020-04-11T23:24:13.000Z",
    "claim": "2020-04-12T23:45:02.946Z",
    "tasks": [
      "E0K2P4CYQouD6mz_4Jlgcg/0",
      "IHpCe0k1RZquArrKJ4K6pg/0"
    ]
  },
  {
    "id": "i-0d3650d9f76efc7c6",
    "launch": "2020-04-11T22:19:28.000Z",
    "claim": "2020-04-12T23:31:44.166Z",
    "tasks": [
      "Jy0v96liSOqpkOpT93BBRw/0",
      "Yq5_F3k8RMum4PmIgK1aGw/0",
      "Z3I7stRPSNuJLq2SxPKssQ/0"
    ]
  },
  {
    "id": "i-07b5deef0dd5fea21",
    "launch": "2020-04-11T23:24:47.000Z",
    "claim": "2020-04-12T23:40:41.805Z",
    "tasks": [
      "ZKdQOhojQbKvwAGttZwXMw/0",
      "UrF6n0jhQDK36M2ehzdeaQ/0"
    ]
  },
  {
    "id": "i-0a599e53749726615",
    "launch": "2020-04-11T23:24:03.000Z",
    "claim": "2020-04-12T23:30:52.758Z",
    "tasks": [
      "WvZuRu0rTMu8wyemYIF5PA/0"
    ]
  },
  {
    "id": "i-07666eff652b70013",
    "launch": "2020-04-11T23:10:35.000Z",
    "claim": "2020-04-12T23:16:52.456Z",
    "tasks": [
      "Wvpy5eDWRAaKjH5_dsAwYA/0"
    ]
  },
  {
    "id": "i-06454d42698c73bc7",
    "launch": "2020-04-11T23:24:07.000Z",
    "claim": "2020-04-12T23:30:50.612Z",
    "tasks": [
      "UsQNCqm6QO62d_0vvoJ8ng/0"
    ]
  },
  {
    "id": "i-0702a2a1aeabc53db",
    "launch": "2020-04-11T23:24:05.000Z",
    "claim": "2020-04-12T23:30:58.979Z",
    "tasks": [
      "b89wPsdGT5WdvDqucMqT3A/0"
    ]
  },
  {
    "id": "i-0732874bc0e2c2060",
    "launch": "2020-04-11T22:18:53.000Z",
    "claim": "2020-04-12T22:25:31.913Z",
    "tasks": [
      "Pz-Oq_ZpSfKVx_7HAb_MJg/0"
    ]
  },
  {
    "id": "i-0eac35e455b8fb47e",
    "launch": "2020-04-11T22:18:47.000Z",
    "claim": "2020-04-12T23:42:58.667Z",
    "tasks": [
      "TT3LpsjcRj-GcyaoR46PFw/0",
      "Wo8RKX9aTG-EJ6b4cgOsaw/0",
      "Kq76zaCyQo6pdJAJdgSuvw/0",
      "M8eE4R5CTuGiPaAWytJIRg/0"
    ]
  },
  {
    "id": "i-0b0922f321245e006",
    "launch": "2020-04-11T23:23:59.000Z",
    "claim": "2020-04-12T23:45:56.814Z",
    "tasks": [
      "U9CzPtD0S963Ingc2ZCF-g/0",
      "Oq2whfsRQfuOZYx39omlsQ/0"
    ]
  },
  {
    "id": "i-0eebd75f1d3fe78ad",
    "launch": "2020-04-11T22:19:34.000Z",
    "claim": "2020-04-12T23:30:37.719Z",
    "tasks": [
      "R5uG_nXiTdC0iDSLSPowhQ/0",
      "RgWpMT4vQX-eYc5wJ1oYew/0",
      "BijNqbEBS8WUnIeOh5RPPQ/0"
    ]
  },
  {
    "id": "i-0ffd8a460bf0dec67",
    "launch": "2020-04-11T23:40:32.000Z",
    "claim": "2020-04-12T23:47:45.927Z",
    "tasks": [
      "b41z7ldISOCCdb-UUhCP5Q/0"
    ]
  },
  {
    "id": "i-043f4f4df4b8119c6",
    "launch": "2020-04-11T23:24:15.000Z",
    "claim": "2020-04-12T23:44:56.065Z",
    "tasks": [
      "XqB0ujIHQje1CGhWSN3WIg/0",
      "GkcroOq-SWy5mYXK5asCTQ/0"
    ]
  },
  {
    "id": "i-0ae94902754e35783",
    "launch": "2020-04-11T23:24:39.000Z",
    "claim": "2020-04-12T23:41:35.950Z",
    "tasks": [
      "dJBZaB4JSNCtImwg_6UWlg/0",
      "Y5q_xCDXSL--jhAudPFgNA/0"
    ]
  },
  {
    "id": "i-0af4ac1ba861a1578",
    "launch": "2020-04-11T22:19:28.000Z",
    "claim": "2020-04-12T23:46:58.227Z",
    "tasks": [
      "Ppvl4bMQS561zKqJNaLzog/0",
      "YQfiRcO5SvOEUQriF7ww-w/0",
      "LCuNfssrSlu7S5Nswk5d_A/0",
      "MWxTW5nNR7ixEuPS_I4ymg/0"
    ]
  },
  {
    "id": "i-0f176d93a498ddee7",
    "launch": "2020-04-11T22:23:38.000Z",
    "claim": "2020-04-12T23:48:01.882Z",
    "tasks": [
      "RvMUDBm8S027q7Hy6_n-QQ/0",
      "cjkJXe2RTqeMmvZyWIWCxg/0",
      "HQM_pzk9ToOEmn1lq94Y9Q/0"
    ]
  },
  {
    "id": "i-00814165ed8ed46df",
    "launch": "2020-04-11T22:01:47.000Z",
    "claim": "2020-04-12T23:46:48.629Z",
    "tasks": [
      "bJRwcWBBSyG6avbs1O13MQ/0",
      "G5KLUeuWSkChST2gPpQNhQ/0",
      "OVOTxd_wRfWfCE7FuxWJGg/0",
      "Q2ogSNlRRB62IEAIm0eJWw/0",
      "O3zwsukkQ6qtFgIWBsYZbw/0"
    ]
  },
  {
    "id": "i-0675e20f288b2590a",
    "launch": "2020-04-11T23:40:32.000Z",
    "claim": "2020-04-12T23:47:43.834Z",
    "tasks": [
      "aOyJZapnQLukauErJkIHsg/0"
    ]
  },
  {
    "id": "i-0e4ea632da3e22dd9",
    "launch": "2020-04-11T23:24:41.000Z",
    "claim": "2020-04-12T23:30:51.854Z",
    "tasks": [
      "WHHH_QpPRsmXehWrqcG0iA/0"
    ]
  },
  {
    "id": "i-07df9f072bea67687",
    "launch": "2020-04-11T23:06:15.000Z",
    "claim": "2020-04-12T23:40:48.206Z",
    "tasks": [
      "dnUeLBbVTKqul9p8LTsxWg/0",
      "UT6mqPcCTTe9bqvzrKAV8A/0"
    ]
  },
  {
    "id": "i-0a1b5e64d71065561",
    "launch": "2020-04-11T22:23:32.000Z",
    "claim": "2020-04-12T23:43:04.755Z",
    "tasks": [
      "N_gp16qzTSiCBdXH7whksw/0",
      "QSanU74NSx6QSdmBhpXoJQ/0",
      "Lmfo09AnSpKomrQEf-jezg/0",
      "NpIj2DvGT7ChM9QqcaSkjg/0"
    ]
  },
  {
    "id": "i-069048efa1007d6bb",
    "launch": "2020-04-11T23:40:30.000Z",
    "claim": "2020-04-12T23:47:18.769Z",
    "tasks": [
      "UtHNYcJGR06Ng4NRzz0hZw/0"
    ]
  },
  {
    "id": "i-099a0d1dccba0584f",
    "launch": "2020-04-11T23:06:12.000Z",
    "claim": "2020-04-12T23:13:19.024Z",
    "tasks": [
      "C6zXcdsFRMeuGx_54vuAbw/0"
    ]
  },
  {
    "id": "i-0f2bf33af0f0b1629",
    "launch": "2020-04-10T21:19:23.000Z"
  },
  {
    "id": "i-05f493c28881cfcfa",
    "launch": "2020-04-11T23:24:03.000Z",
    "claim": "2020-04-12T23:40:26.079Z",
    "tasks": [
      "dgMUVe-ZQ8C8hnTA_riH8g/0",
      "RleDlX5QSciHp91LOuDvPQ/0"
    ]
  },
  {
    "id": "i-0691e55ee075bbbc8",
    "launch": "2020-04-11T23:10:59.000Z",
    "claim": "2020-04-12T23:17:17.906Z",
    "tasks": [
      "amtYm7zNRASkhYU2oGfvxQ/0",
      "AKYVpK08SfKBBiW-lOMa0Q/0"
    ]
  },
  {
    "id": "i-041701c7ee3310269",
    "launch": "2020-04-11T23:23:55.000Z",
    "claim": "2020-04-12T23:44:51.489Z",
    "tasks": [
      "FvEB8lAyQTehSscAO8EvsQ/0",
      "EEt446eQQ4WiaCYSCzPvbw/0"
    ]
  },
  {
    "id": "i-02aa94b770f09a789",
    "launch": "2020-04-11T23:24:03.000Z",
    "claim": "2020-04-12T23:31:01.840Z",
    "tasks": [
      "bQGGIRfLT9Se7fQ5-osPhw/0"
    ]
  },
  {
    "id": "i-0f3027ee2c0f44a1a",
    "launch": "2020-04-11T23:06:07.000Z",
    "claim": "2020-04-12T23:40:51.742Z",
    "tasks": [
      "QMiMn7agSdO4pDP_Tm3ezw/0",
      "JI8KVgCuSBCmhyLRjW6nIw/0"
    ]
  },
  {
    "id": "i-0a8a519754ded0498",
    "launch": "2020-04-11T22:19:02.000Z",
    "claim": "2020-04-12T23:48:20.722Z",
    "tasks": [
      "Q7EWiztpSfy_tmLNC26Mgg/0",
      "a6NABBUHRoKF4MFjNuPyAg/0",
      "N0l_ZxRITcK3YrS8S87Qow/0",
      "ZhFrAUToRM-0Ih5L2t7y6A/0"
    ]
  },
  {
    "id": "i-0dde26f102e17e876",
    "launch": "2020-04-11T23:23:59.000Z",
    "claim": "2020-04-12T23:30:56.459Z",
    "tasks": [
      "aEaQhI-9SAOTRuknAyYvlQ/0",
      "eNz8Ai3wSCenooT5ex-6bQ/0"
    ]
  },
  {
    "id": "i-08d83b5e7fea44b4c",
    "launch": "2020-04-11T22:23:32.000Z",
    "claim": "2020-04-12T23:24:56.392Z",
    "tasks": [
      "YXV_vYJmRwaqb9WUFH06ZQ/0",
      "dz3P-nIwSOmNhSqqRtFDfw/0",
      "FL713NSRRJ6CuiYpYssHkw/0"
    ]
  },
  {
    "id": "i-0980de9440abf39d5",
    "launch": "2020-04-11T23:40:24.000Z",
    "claim": "2020-04-12T23:47:22.882Z",
    "tasks": [
      "XV8_TA3VQ8CvRSZ3YDBMHw/0"
    ]
  },
  {
    "id": "i-058826c3172131d60",
    "launch": "2020-04-11T22:18:52.000Z",
    "claim": "2020-04-12T23:45:39.673Z",
    "tasks": [
      "XUhMUGMQQ2CSWXmNwEtIjA/0",
      "B998x5ysRA-V7LSHz7bRTg/0",
      "IV50guMNTU-GrcN6HjgBhw/0"
    ]
  },
  {
    "id": "i-0f8e8823798b483ce",
    "launch": "2020-04-09T04:07:17.000Z"
  },
  {
    "id": "i-0fcda3316fd5ab91e",
    "launch": "2020-04-11T22:19:28.000Z",
    "claim": "2020-04-12T23:44:38.250Z",
    "tasks": [
      "b9dj2pMcRayCvulR8vgJ_Q/0",
      "andWF7C3SEi90vy1XZutJg/0",
      "JdIedPK_TM2v98UXeDLQ7A/0",
      "RXFR675RRG-1JVU4D7LSVA/0"
    ]
  },
  {
    "id": "i-0a09b334c8c51e9be",
    "launch": "2020-04-11T23:24:44.000Z",
    "claim": "2020-04-12T23:31:55.613Z",
    "tasks": [
      "ZCLIFljVRAW3GXlfAklq3g/0"
    ]
  },
  {
    "id": "i-08c0a6bd46f63b0eb",
    "launch": "2020-04-11T23:40:34.000Z",
    "claim": "2020-04-12T23:47:43.819Z",
    "tasks": [
      "a2tSzCQ1Q9CX4pZPPHDcFA/0"
    ]
  },
  {
    "id": "i-006e0f26539c95d31",
    "launch": "2020-04-11T23:24:13.000Z",
    "claim": "2020-04-12T23:47:48.206Z",
    "tasks": [
      "D50AWgciRCiMckoFXRF4DA/0",
      "S6KE-8S4TaKDneP3shJo2Q/0"
    ]
  },
  {
    "id": "i-00312077ed075d7b7",
    "launch": "2020-04-11T22:19:39.000Z",
    "claim": "2020-04-12T23:39:57.591Z",
    "tasks": [
      "H-C9C0fQS8K8MHQlQMKQzA/0",
      "fCn_Ao7fTtC633t3I0-pzA/0",
      "AZxVtFpbRn-njb9hh2g3Xg/0"
    ]
  },
  {
    "id": "i-07fe07c2d1bbc03ba",
    "launch": "2020-04-11T22:23:40.000Z",
    "claim": "2020-04-12T23:45:07.396Z",
    "tasks": [
      "RhIJdveBTsSJSXzKA7GgMQ/0",
      "EFKiKqwITZ-e-TSOMVUt0A/0",
      "bp9vQ3fkQxmx6lN_kCaBrQ/0",
      "IfJUqmjqQeqUISBGVzA3ZA/0"
    ]
  },
  {
    "id": "i-09742a65a2f28f074",
    "launch": "2020-04-11T23:06:10.000Z",
    "claim": "2020-04-12T23:33:56.739Z",
    "tasks": [
      "DIvep-6KRmqGl_PfjUqUDQ/0",
      "anGglZPLQDqmZ2UafNUYvw/0"
    ]
  },
  {
    "id": "i-0e9e30633b2a2bfb3",
    "launch": "2020-04-11T23:23:51.000Z",
    "claim": "2020-04-12T23:44:23.337Z",
    "tasks": [
      "SAv8ZGZTQf6KctkUSH8nVw/0",
      "IrjzkhTnR3G0kWhmFEvjMQ/0"
    ]
  },
  {
    "id": "i-0648b413480b7f7ee",
    "launch": "2020-04-11T23:10:37.000Z",
    "claim": "2020-04-12T23:17:06.642Z",
    "tasks": [
      "b0p277dQSma4XtEtaBmyZg/0"
    ]
  },
  {
    "id": "i-074fa2721add000c3",
    "launch": "2020-04-11T22:23:53.000Z",
    "claim": "2020-04-12T23:41:52.997Z",
    "tasks": [
      "RRhNm47WR9q8PALw6Kfm3w/0",
      "Dw1856kZSlmRKhAsbvnQ9g/0",
      "XgeDmxjwQhWxcviih8cgKQ/0",
      "POjY8RN_Q0ip26YwcW0sGg/0"
    ]
  },
  {
    "id": "i-02934cde94d24da9a",
    "launch": "2020-04-11T22:01:42.000Z",
    "claim": "2020-04-12T23:44:34.077Z",
    "tasks": [
      "cwZieQKvSEKulmngbAVKNw/0",
      "KmoW1kThSLy4ncrC01FSHA/0",
      "PzO6PNDSSuKIxSdQdxOcTg/0",
      "Zmeu8NXnTgSD2eJ8lIrTDA/0"
    ]
  },
  {
    "id": "i-041e26b7f9a3a3e91",
    "launch": "2020-04-11T22:18:47.000Z",
    "claim": "2020-04-12T23:43:04.010Z",
    "tasks": [
      "N4WL05i8QkKMspSmMTGOkA/0",
      "Kp3j37KQQuGgt80tEBXnUQ/0",
      "M0EGq8sxTmSCx_tZvMadGA/0"
    ]
  },
  {
    "id": "i-00d1e1c0ad98c0f37",
    "launch": "2020-04-11T23:40:26.000Z",
    "claim": "2020-04-12T23:47:25.560Z",
    "tasks": [
      "e0Ep-x7DQQCFwa9wpiDoig/0"
    ]
  },
  {
    "id": "i-0880c1a947955c34c",
    "launch": "2020-04-11T23:23:55.000Z",
    "claim": "2020-04-12T23:44:53.073Z",
    "tasks": [
      "ISP2Gs99SP2M3q-rPHAMzQ/0",
      "HPfcFAjbS1emmsd7agEZGQ/0"
    ]
  },
  {
    "id": "i-01e01469f0d0f4814",
    "launch": "2020-04-11T23:24:05.000Z",
    "claim": "2020-04-12T23:47:48.320Z",
    "tasks": [
      "KSZXZG2eRrOF4ZhjwLuItQ/0",
      "OPg4ITrlQxuWL3YmJ2_lBw/0"
    ]
  },
  {
    "id": "i-02a2ec528485f28f8",
    "launch": "2020-04-11T23:23:55.000Z",
    "claim": "2020-04-12T23:30:44.874Z",
    "tasks": [
      "NdvBS0KfSB-aIWG4Mw3WSA/0"
    ]
  },
  {
    "id": "i-0bdaef3717c398f42",
    "launch": "2020-04-11T23:40:34.000Z",
    "claim": "2020-04-12T23:47:47.813Z",
    "tasks": [
      "ERi7Mv9IRZe-8Izpzs2Shw/0"
    ]
  }
]