{
  "claim": "2020-04-14T07:57:55.021Z",
  "expires": "2020-04-15T12:00:24.930Z",
  "tasks": [
    {
      "task": "GgazVTP0Rr-Bn80kUd8o8A",
      "run": 0
    },
    {
      "task": "a0YWRyj1RuCONf81WMj0MQ",
      "run": 0
    },
    {
      "task": "G_0xTF6ISLOw7SCUg5ouyQ",
      "run": 0
    },
    {
      "task": "fgTJGIHVQ1Ogsvltr7m-Sg",
      "run": 0
    },
    {
      "task": "Jm_McuUIQ4Ok8_Nh0QyqPA",
      "run": 0
    },
    {
      "task": "CUp5u2cwTvy4ZYM0cEab0g",
      "run": 0
    },
    {
      "task": "Fk7dTPdFRqmOn6Xk_YSi5g",
      "run": 0
    },
    {
      "task": "IwyDZ1lPRs-wUNPDt6AsKg",
      "run": 0
    },
    {
      "task": "PvNXPVe8T_q4Jdqf4lMiXw",
      "run": 0
    }
  ]
}