{
  "claim": "2020-04-15T08:24:41.340Z",
  "expires": "2020-04-16T09:26:40.120Z",
  "tasks": [
    {
      "task": "IR5x_R41QjmuUGCH5psxZQ",
      "run": 0
    },
    {
      "task": "Ict8-qZvRtWyD66Z8en20g",
      "run": 0
    },
    {
      "task": "A-4CjpgZQOerE8RYTECzpQ",
      "run": 0
    },
    {
      "task": "H5PZqVXXSHuBxm1GOMnZPA",
      "run": 0
    },
    {
      "task": "Fy2NRDA1Syu4NTNtzfrRng",
      "run": 0
    },
    {
      "task": "Dai-MPW1QYuMKFDCkY1vcw",
      "run": 0
    },
    {
      "task": "Tf4qrBL0SQC3ZeuXBjWmgQ",
      "run": 0
    },
    {
      "task": "fWdLK1WDTRuJcZ67X6FSTQ",
      "run": 0
    }
  ]
}