{
  "claim": "2020-04-07T13:53:00.023Z",
  "expires": "2020-04-08T15:16:06.373Z",
  "tasks": [
    {
      "task": "OtesGtH_TrO_dAl8LJl5nQ",
      "run": 0
    },
    {
      "task": "W1r6H4O4SUyshk2r_K3RgA",
      "run": 0
    },
    {
      "task": "JjoZ5u2lTQ-9ADdNo6QTUQ",
      "run": 0
    },
    {
      "task": "CiPNPBAiSzGgcdkTLo6TlA",
      "run": 0
    },
    {
      "task": "SAawl_JjTLCQuYSnGb_zKA",
      "run": 0
    },
    {
      "task": "ERd4r7BQSIWSr2WsDC0dMw",
      "run": 0
    }
  ]
}