{
  "claim": "2020-04-07T10:16:17.435Z",
  "expires": "2020-04-08T12:08:21.434Z",
  "tasks": [
    {
      "task": "N9xsHnGJT9mNdmgdOdIlxQ",
      "run": 0
    },
    {
      "task": "J0j6Qz-fRU2SXyE7sJc8Bw",
      "run": 0
    },
    {
      "task": "KvLZFU-ZQKWivjqK_cIDcA",
      "run": 0
    },
    {
      "task": "NOfkhIG6QaGV-BhV_CTU8g",
      "run": 0
    },
    {
      "task": "IkwmC9UiR3uPCTfhU0RuSg",
      "run": 0
    },
    {
      "task": "RTd4961_S9aYfvQFOZuiXQ",
      "run": 0
    },
    {
      "task": "WVSwln4ZSKSs3qoBXR-Ktw",
      "run": 0
    },
    {
      "task": "Q6hMiI0dTIqVyCwVnwxMFA",
      "run": 0
    }
  ]
}