{
  "claim": "2020-04-14T21:33:46.856Z",
  "expires": "2020-04-15T22:52:21.736Z",
  "tasks": [
    {
      "task": "CUzIZOc3RIOrwHRqWqFdgw",
      "run": 0
    },
    {
      "task": "eBjF8CuTSougikZulU3wOQ",
      "run": 0
    },
    {
      "task": "EjIukm-IQ5CgjN17CPWArQ",
      "run": 0
    },
    {
      "task": "V3us4Q6TSwi2OYaoEDofeg",
      "run": 0
    },
    {
      "task": "Lw_A8DpoTT2D_l2jByCL9Q",
      "run": 0
    },
    {
      "task": "XLia27KyRCaXuU0_-0aMSg",
      "run": 0
    }
  ]
}