{
  "claim": "2020-04-08T09:57:13.530Z",
  "expires": "2020-04-09T11:38:21.821Z",
  "tasks": [
    {
      "task": "fK5hXkGpQi65Iq0uJMVFGw",
      "run": 0
    },
    {
      "task": "H8NB-5LpTCSjVyFbiun5kA",
      "run": 0
    },
    {
      "task": "CYTEdI-sRwqxp-YbKdU4oQ",
      "run": 0
    },
    {
      "task": "Iiqe9PsnQ66CsD4PCkAreg",
      "run": 0
    },
    {
      "task": "LzHkigFPTWaV3I3uAZXIfQ",
      "run": 0
    },
    {
      "task": "SMiGD9wgT76PrerZaU3aqw",
      "run": 0
    },
    {
      "task": "KcEaPRCDS-qHuVwx1ooXEQ",
      "run": 0
    },
    {
      "task": "a_iM4_IWS5-PdQCL_k4c7Q",
      "run": 0
    },
    {
      "task": "ObPyoKXHQwOmnv2VZeO7Sg",
      "run": 0
    }
  ]
}