{
  "claim": "2020-04-06T18:01:23.732Z",
  "expires": "2020-04-07T21:04:13.611Z",
  "tasks": [
    {
      "task": "R2nhQy9uQbKSF_B8CQ8g3w",
      "run": 0
    },
    {
      "task": "G-BMIDcKRT6VFALh5Dh6cA",
      "run": 0
    },
    {
      "task": "DnbsQz_NSNCHXXENKbbUjQ",
      "run": 0
    },
    {
      "task": "X1v4_LeKS9OUnD6EWtK-KA",
      "run": 0
    },
    {
      "task": "elHpR5IuRbqH8TdqJu-QoQ",
      "run": 0
    },
    {
      "task": "DR0H5ENtQIuZtYk2q9zVRw",
      "run": 0
    },
    {
      "task": "V9mYZ9f1THe44EMBmjgSNQ",
      "run": 0
    },
    {
      "task": "WSQ1PWH5SfagKLj8D2Q8Eg",
      "run": 0
    },
    {
      "task": "I8vASYS2RXaVsXoGGx5hMQ",
      "run": 0
    },
    {
      "task": "P_xNjZLtS2Swz_KrIPYUzg",
      "run": 0
    },
    {
      "task": "TbCCI50MRTK4y0HNDoxS_g",
      "run": 0
    },
    {
      "task": "Z5rl5_qxQI-0-SaJiArFZw",
      "run": 0
    },
    {
      "task": "FgvOQ0M9RyGz-MShQrFlHQ",
      "run": 0
    }
  ]
}