{
  "claim": "2020-04-13T17:30:41.384Z",
  "expires": "2020-04-14T19:49:45.248Z",
  "tasks": [
    {
      "task": "WeOxmLNfTFGasQ4b03oQ6g",
      "run": 0
    },
    {
      "task": "FfvVbZ2FSW-JYm9gZ6zxPA",
      "run": 0
    },
    {
      "task": "Z3Ye1ngqRnODpcDAoqH83Q",
      "run": 1
    },
    {
      "task": "Mw8ZUoYaSAur6zBHrBJdxQ",
      "run": 0
    },
    {
      "task": "KbK3LsFoSt6fI1r9q1ibXg",
      "run": 0
    },
    {
      "task": "H-1wO3vOT9Ol0NKSym0Qpg",
      "run": 0
    }
  ]
}