{
  "claim": "2020-04-20T04:07:37.362Z",
  "expires": "2020-04-21T05:04:31.719Z",
  "tasks": [
    {
      "task": "eTLSYNyBSgeoulOPDHnImw",
      "run": 0
    },
    {
      "task": "fqdVzgHxQAG4OyuZPx1GgA",
      "run": 0
    },
    {
      "task": "c09mhJcxQd6_r3lIAr-uAw",
      "run": 0
    },
    {
      "task": "JYgqXB-nSH21dVP3TA_usg",
      "run": 0
    },
    {
      "task": "ORBIg7hnQHGZPGCPD6yeug",
      "run": 0
    },
    {
      "task": "euMCHS4GRFaCRLTA4h3ccg",
      "run": 0
    },
    {
      "task": "eCnJc3kvQM6GweTZD0Z4Ng",
      "run": 1
    },
    {
      "task": "WhfOSPF_Q4ms41nHCo659Q",
      "run": 1
    },
    {
      "task": "Tt8EfOi8RjqkjBP-ND8_Ew",
      "run": 0
    },
    {
      "task": "A9BJXaI3S8CjUT02BpEQrw",
      "run": 0
    },
    {
      "task": "BHDTFhHWQJm-KEy7AFWjnw",
      "run": 0
    }
  ]
}