{
  "claim": "2020-04-21T16:01:54.711Z",
  "expires": "2020-04-22T18:55:10.352Z",
  "tasks": [
    {
      "task": "aDkRubWCTBGhF_McFDI3hg",
      "run": 0
    },
    {
      "task": "Wl99PwVeSyuZsohrtT0o_g",
      "run": 1
    },
    {
      "task": "MCmxhXiGSWOXxIuidks5Fg",
      "run": 1
    },
    {
      "task": "crqcI-eeT9a7Oeze6pNO6g",
      "run": 0
    },
    {
      "task": "HtaDP7npQeqD9KTdUZnYsg",
      "run": 0
    },
    {
      "task": "CfvRSSh5SbKuakgcg55e_A",
      "run": 0
    },
    {
      "task": "ayggpg5YSVCRCK9G7pXXnA",
      "run": 0
    }
  ]
}