{
  "claim": "2020-04-21T12:50:13.071Z",
  "expires": "2020-04-22T13:59:20.031Z",
  "tasks": [
    {
      "task": "Ddl1smKMR3yRmJ-qclQD9A",
      "run": 0
    },
    {
      "task": "ZI16lYsKTp2uWXuekV3nQw",
      "run": 0
    },
    {
      "task": "dKVUjE38Q52DuZbfe9oQpQ",
      "run": 0
    },
    {
      "task": "f5lPBoHISwGUk8pnI0YdPg",
      "run": 0
    },
    {
      "task": "evC9mkYxS6uJL3dS5Fkhsw",
      "run": 0
    },
    {
      "task": "ICjBYZMiTrqKHNZFhKnDFw",
      "run": 0
    }
  ]
}