{
  "claim": "2020-04-22T13:00:48.524Z",
  "expires": "2020-04-23T14:49:50.411Z",
  "tasks": [
    {
      "task": "eBVPVAiARS6pDjfRbh6wzA",
      "run": 0
    },
    {
      "task": "QYuk7GbaTomZxncaeOQiMQ",
      "run": 0
    },
    {
      "task": "ZGw-nuMvQ7e_35ZW_-Nyew",
      "run": 0
    },
    {
      "task": "SC6CUwWTSTGX9U1ZUdvdrg",
      "run": 0
    },
    {
      "task": "BVPCkj7AQrmpaY5e7NxEcg",
      "run": 0
    },
    {
      "task": "R8VHZ__CQJWDQSFSZkSMQw",
      "run": 0
    },
    {
      "task": "TAajjz32RbG1uERnhrGZlw",
      "run": 0
    },
    {
      "task": "A0njC8HHSH-ix6McDgwYtg",
      "run": 0
    },
    {
      "task": "Xqgwbc7pSKarRy8e_9-p8Q",
      "run": 1
    }
  ]
}