{
  "claim": "2020-04-08T21:53:09.904Z",
  "expires": "2020-04-09T23:36:23.148Z",
  "tasks": [
    {
      "task": "BkhalCBIQ9efTFKzKF-COQ",
      "run": 0
    },
    {
      "task": "DJQovTMZTf6PeQuMmkJzmg",
      "run": 0
    },
    {
      "task": "WSdNSCBGTESCNUTNkhPDzg",
      "run": 0
    },
    {
      "task": "dzzThTFYS8ydVgqLM8qCRQ",
      "run": 0
    },
    {
      "task": "KnUltVlDShuKq0gHW6UiTA",
      "run": 0
    },
    {
      "task": "c1nQaJzDQeyEjCP5J3myQA",
      "run": 0
    },
    {
      "task": "NOYULDjBTECjS62KG7qvpQ",
      "run": 0
    }
  ]
}