{
  "claim": "2020-04-21T11:53:28.688Z",
  "expires": "2020-04-22T14:31:46.580Z",
  "tasks": [
    {
      "task": "V4nTLkbRTc68h_U4Tr3gBw",
      "run": 0
    },
    {
      "task": "fn0PmulxQPeqVEtvLQL5XA",
      "run": 0
    },
    {
      "task": "a7ZBv-gfRNuqd9UL__HzhQ",
      "run": 0
    },
    {
      "task": "GYHKq3rsRAKXTOkd8pPCrg",
      "run": 0
    },
    {
      "task": "MU5wwvyaSsaV4AdFGN67Cw",
      "run": 0
    },
    {
      "task": "PwnIlSLwR0ueMwjgW1fYDw",
      "run": 0
    },
    {
      "task": "FEyMWzlkQwmt3LFsk3SIeA",
      "run": 0
    },
    {
      "task": "fLLRnvYzTFqHYd__E7DDwg",
      "run": 0
    }
  ]
}