{
  "claim": "2020-04-21T16:47:29.327Z",
  "expires": "2020-04-22T21:05:14.564Z",
  "tasks": [
    {
      "task": "MfgQSoiqT-iYr27ar9vZSA",
      "run": 0
    },
    {
      "task": "SUIalkD4TV2uoyvH9tby_A",
      "run": 1
    },
    {
      "task": "fjdf82OuSxelbWzg6dJghQ",
      "run": 0
    },
    {
      "task": "H__3z3rVTWCEyiHR7ISW8g",
      "run": 0
    },
    {
      "task": "eQKgPC8RRniN719fZQKpng",
      "run": 0
    },
    {
      "task": "ddkq-cJgQ2WPfcVt4UnP9g",
      "run": 0
    },
    {
      "task": "IURNW7J2TTSy30_ZnGaRdA",
      "run": 0
    },
    {
      "task": "USznxEuXSES393Y-VFwVLQ",
      "run": 0
    },
    {
      "task": "bVx1EM9eTUKm1M6W6TCwVw",
      "run": 0
    },
    {
      "task": "CdcdRcC3TXKDZ8zzQ_QnUA",
      "run": 0
    },
    {
      "task": "VOgP5-34QDCN2y8Sm_v9rg",
      "run": 0
    },
    {
      "task": "OuAN7VMrQcizLrB_8oKTzg",
      "run": 0
    }
  ]
}