{
  "claim": "2020-04-07T16:41:20.097Z",
  "expires": "2020-04-08T20:00:06.282Z",
  "tasks": [
    {
      "task": "PzH6OXWQQta5J4K4buFWLw",
      "run": 0
    },
    {
      "task": "dnh0NJUxQnOYT3vaMyQxcw",
      "run": 0
    },
    {
      "task": "cEDtdCKWT9igm8OgLLpTrQ",
      "run": 0
    },
    {
      "task": "aXuW1jCFTMSfOsw9Jsc88g",
      "run": 0
    },
    {
      "task": "Rga7NBDgSImPRLRyOwIlhg",
      "run": 0
    },
    {
      "task": "JV0DIzCnRTaP8n2vBUhhCg",
      "run": 0
    },
    {
      "task": "O_IrYC74Snq8vIcrSzv5nA",
      "run": 0
    }
  ]
}