{
  "claim": "2020-04-09T06:12:18.566Z",
  "expires": "2020-04-10T11:27:52.636Z",
  "tasks": [
    {
      "task": "QBALzWSGQPyJUQy7xGLVFA",
      "run": 0
    },
    {
      "task": "Km77WVe1RDOzGdEJZq_rOQ",
      "run": 0
    },
    {
      "task": "L5ev3gmZSJOjTgocWugybQ",
      "run": 0
    },
    {
      "task": "MlsH8iNSTtmovi3j8vp_Sw",
      "run": 0
    },
    {
      "task": "eFcPYeDRTHOTDAmaH1onmg",
      "run": 0
    },
    {
      "task": "aUWEd78nTXuRyCKf4ztKFQ",
      "run": 0
    },
    {
      "task": "CtpmFLhdQmWtg5VG3TybUQ",
      "run": 0
    }
  ]
}