{
  "claim": "2020-04-17T15:20:42.216Z",
  "expires": "2020-04-18T18:08:54.385Z",
  "tasks": [
    {
      "task": "cI8Eeg_GTqWycg9TxArBnw",
      "run": 0
    },
    {
      "task": "Gc0smJvUQAGx8-xKYXKIcA",
      "run": 0
    },
    {
      "task": "GB55foOkQTGpeC3T_G3SSQ",
      "run": 0
    },
    {
      "task": "X9wZYqZtRECOxPhUWLubUQ",
      "run": 1
    },
    {
      "task": "cHouzztYTYOh65qHW5UkFg",
      "run": 0
    },
    {
      "task": "bD750UZQRSyZ--Eh38X2Ig",
      "run": 0
    }
  ]
}