{
  "claim": "2020-04-20T14:43:06.017Z",
  "expires": "2020-04-21T18:21:03.979Z",
  "tasks": [
    {
      "task": "NSRLIsE1S3O-u_HdUA7bXg",
      "run": 0
    },
    {
      "task": "DG2vnYi_QtKR7VmYdovAuA",
      "run": 0
    },
    {
      "task": "SfBpzNTpSousH-RhbGk5Zg",
      "run": 0
    },
    {
      "task": "R0KQKDG8TkKU_ZtwGWu8Ow",
      "run": 0
    },
    {
      "task": "W9GGnpKKR-mJRPbrOQeUgA",
      "run": 0
    },
    {
      "task": "XV4cKnqWRV2CmAoGN1BhXw",
      "run": 0
    },
    {
      "task": "Kt6Wg1-NT-u2QmdPQYBALA",
      "run": 0
    },
    {
      "task": "XAPgU2zvQ3u2mTj-NermWA",
      "run": 0
    },
    {
      "task": "ZsqiuSaYSNazS8OnmHg0Bw",
      "run": 0
    },
    {
      "task": "KJt8divwR6iAKqDwGw3N1g",
      "run": 0
    },
    {
      "task": "LcR7kZcnQHuQ0-vfsdbNYw",
      "run": 1
    }
  ]
}