{
  "claim": "2020-04-21T22:14:56.522Z",
  "expires": "2020-04-23T01:00:08.296Z",
  "tasks": [
    {
      "task": "bTDneYDZR8qcrZHDjx_nYw",
      "run": 0
    },
    {
      "task": "aJHIXUQwQqOFoJdj3PRJuQ",
      "run": 0
    },
    {
      "task": "chsI0N46RoS1D9sxwjhgGw",
      "run": 0
    },
    {
      "task": "KLpoaC1XR22Tb-pHTCWdmA",
      "run": 0
    },
    {
      "task": "CvlSdy7HTgCE9SJ_jVb_iQ",
      "run": 0
    },
    {
      "task": "TgDaqIVMSb6qNXxrLTEiaQ",
      "run": 0
    },
    {
      "task": "c8GJkxofTGetIxVnLBqZpQ",
      "run": 0
    }
  ]
}