{
  "claim": "2020-04-20T04:53:59.126Z",
  "expires": "2020-04-21T05:10:42.475Z",
  "tasks": [
    {
      "task": "MCGfhygXSmicNTFeumsNgA",
      "run": 0
    },
    {
      "task": "alee01oHTHi33KkGP7D2qg",
      "run": 0
    },
    {
      "task": "XUeYLwuyQ8i4iiRGHdpt6Q",
      "run": 0
    },
    {
      "task": "G-d-ORZfT-SzC1H3-6wWxw",
      "run": 0
    },
    {
      "task": "afMuRqYwS8GeyQa47TQx-Q",
      "run": 0
    },
    {
      "task": "M_amx5QVRveCSlDFKRs96A",
      "run": 0
    },
    {
      "task": "Lb_B9sMMQGGnexPPoDN_NQ",
      "run": 0
    },
    {
      "task": "WZKUVapST66Xe5WWvYiLZw",
      "run": 0
    },
    {
      "task": "THKMwsowQv-uaJ7hGz9RJA",
      "run": 0
    }
  ]
}