{
  "claim": "2020-04-22T17:56:35.700Z",
  "expires": "2020-04-23T23:41:09.853Z",
  "tasks": [
    {
      "task": "ZjVeaTScRNKaHcSrCWGT3w",
      "run": 0
    },
    {
      "task": "WIUmKuXOQRq4lr3pXQ-mSg",
      "run": 0
    },
    {
      "task": "CACd_KWjTTK_awIryWs-uQ",
      "run": 1
    },
    {
      "task": "YId2qyINTduoJltUcM6UyA",
      "run": 0
    },
    {
      "task": "B4k2wTzlTfqRr5mZ5Z978w",
      "run": 0
    },
    {
      "task": "Amg9mGcCS-G_PAePturyow",
      "run": 0
    },
    {
      "task": "Q2imVc9JSMagiEtBM84tYg",
      "run": 0
    },
    {
      "task": "X8L1DEhKQvauvgXm8kq6VQ",
      "run": 0
    },
    {
      "task": "cUteXeRQQQ-SGzEOsEC7jA",
      "run": 0
    },
    {
      "task": "eI_HEyelRqeOC1Q_84Qvjw",
      "run": 0
    },
    {
      "task": "CiEws5c4Ss6QbW2RIge0KA",
      "run": 0
    },
    {
      "task": "dfcQ7t3XT2268Uf-Yne7_w",
      "run": 0
    },
    {
      "task": "GS8pyJ2YQSKL6m4lX_1yLQ",
      "run": 0
    },
    {
      "task": "Si00YZ1fQLSqq7n0Oms6fw",
      "run": 0
    },
    {
      "task": "SsbGabijSJesbVEBhg2dTg",
      "run": 0
    },
    {
      "task": "PTFt3y2bS-yyc5R4dDkagA",
      "run": 0
    },
    {
      "task": "ALiv3MQ5RXqc72CcrNMjow",
      "run": 0
    },
    {
      "task": "BXBpQ_ezSFuaWUq7J8acmA",
      "run": 0
    },
    {
      "task": "fnL3QS-rSCGWa0ZowSFsmg",
      "run": 0
    },
    {
      "task": "Mg7ZtL0vRz-v8ofQDZHvfQ",
      "run": 0
    }
  ]
}