{
  "claim": "2020-04-20T23:24:39.348Z",
  "expires": "2020-04-21T23:59:27.636Z",
  "tasks": [
    {
      "task": "J4_akAZeTnWnmxQAVPua5g",
      "run": 0
    },
    {
      "task": "Pan3ZL2ERUa6q5sCrXOiuA",
      "run": 0
    },
    {
      "task": "fBHVx9K9QfSBytL2EYNRjg",
      "run": 0
    },
    {
      "task": "IjphJDviQFKQWkcCKL_C9A",
      "run": 0
    },
    {
      "task": "dUdUepkMStmn45W5gWg31A",
      "run": 0
    },
    {
      "task": "HUJuSGx2Ski5hqb9yBIoEA",
      "run": 0
    },
    {
      "task": "eYLTOMpdQKSgpXRcgjzSRA",
      "run": 0
    }
  ]
}