{
  "claim": "2020-04-16T18:02:10.250Z",
  "expires": "2020-04-18T01:31:13.121Z",
  "tasks": [
    {
      "task": "JgnjCV79Sr6ConKDWIRCXw",
      "run": 0
    },
    {
      "task": "dVM8o6ngToeMtulGtdg63A",
      "run": 1
    },
    {
      "task": "J5KrZ9KdR5e8oYS9ZSdi8w",
      "run": 0
    },
    {
      "task": "EeX-JgzURJ2r7FLV2d8KIQ",
      "run": 0
    },
    {
      "task": "OIoUl9PbRiqdxUOeqhg6Ig",
      "run": 1
    },
    {
      "task": "cByd5ev3RL69Le1wSjKCNg",
      "run": 0
    },
    {
      "task": "KmINmYtIQI283MeXeuohcg",
      "run": 0
    },
    {
      "task": "XxUvx0TJRYOPr9qvFopDUw",
      "run": 0
    },
    {
      "task": "P0yzhZYBSDG55jKeZ0eCwA",
      "run": 0
    },
    {
      "task": "DKaZeL3wRmqZgOv0juvrng",
      "run": 0
    },
    {
      "task": "T2miUDKyQtWyqBv_GrSnnA",
      "run": 0
    },
    {
      "task": "PwVOC91hT1WxJ7KAkIPh2w",
      "run": 0
    },
    {
      "task": "OCo6pzq1QpGU1K5_mXm3VA",
      "run": 0
    },
    {
      "task": "X6QEAZgjRpW2M-rBM-Eb2A",
      "run": 0
    },
    {
      "task": "bKJOtIStRcSr5oksZxHk-Q",
      "run": 0
    },
    {
      "task": "R2vsLj9pR_qMB-ZdI9AdWQ",
      "run": 0
    },
    {
      "task": "TTkTFjHkSfapToPWw4YXkw",
      "run": 0
    },
    {
      "task": "PZ-vppAmRUq_ZJ-9QDVfYg",
      "run": 0
    },
    {
      "task": "cs1mr4lKQdOTyR3uHBKuew",
      "run": 0
    }
  ]
}